{
    "$schema": "https://schema.management.azure.com/schemas/2015-01-01/deploymentParameters.json#",
    "contentVersion": "1.0.0.0",
    "parameters": {
      "location": {
        "value": "westeurope"
      },
      "environmentType": {
        "value": "dev"
      },
      "project": {
        "value": "abc"
      },
      "computerName": {
        "value": "cebsdevops"
      },
      "adminUsername": {
        "value": "logitech"
      },
      "keyVaultName": {
        "value": "kv-ubuntu"
      },
      "keyVaultRGName": {
        "value": "kv-ubuntu"
      }
    }
  }